cumtime.py
cumtime-0.3.0.dist-info/METADATA
cumtime-0.3.0.dist-info/WHEEL
cumtime-0.3.0.dist-info/top_level.txt
cumtime-0.3.0.dist-info/RECORD
