Metadata-Version: 2.1
Name: cumtime
Version: 0.3.0
Summary: Cumulative measurement of execution time
Home-page: https://github.com/atsuoishimoto/cumtime.py
Author: Atsuo Ishimoto
License: UNKNOWN
Project-URL: Bug Reports, https://github.com/atsuoishimoto/cumtime.py/issues
Project-URL: Source, https://github.com/atsuoishimoto/cumtime.py
Keywords: cumtime
Platform: UNKNOWN
Classifier: Development Status :: 5 - Production/Stable
Classifier: Intended Audience :: Developers
Classifier: License :: OSI Approved :: MIT License
Classifier: Programming Language :: Python :: 3
Requires-Python: >=3.6
